qdjarv/__init__.py
qdjarv-0.1.1.dist-info/LICENSE
qdjarv-0.1.1.dist-info/METADATA
qdjarv-0.1.1.dist-info/WHEEL
qdjarv-0.1.1.dist-info/top_level.txt
qdjarv-0.1.1.dist-info/RECORD
