Metadata-Version: 2.1
Name: qdjarv
Version: 0.1.1
Summary: Quick and dirty jsonapi response validator
Home-page: https://github.com/Wesmania/qdjarv
Author: Igor Kotrasinski
Author-email: i.kotrasinsk@gmail.com
License: MIT
Platform: UNKNOWN
Classifier: Programming Language :: Python :: 3
Classifier: License :: OSI Approved :: MIT License
Classifier: Operating System :: OS Independent
Classifier: Development Status :: 2 - Pre-Alpha
Requires-Python: >=3.6
